{
  "version": "7",
  "dialect": "postgresql",
  "entries": [
    {
      "idx": 0,
      "version": "7",
      "when": 1750599892784,
      "tag": "0000_curvy_millenium_guard",
      "breakpoints": true
    },
    {
      "idx": 1,
      "version": "7",
      "when": 1750601307614,
      "tag": "0001_lively_johnny_storm",
      "breakpoints": true
    },
    {
      "idx": 2,
      "version": "7",
      "when": 1750673979251,
      "tag": "0002_blue_fallen_one",
      "breakpoints": true
    }
  ]
}